[{"movieId":141.0,"title":"Saving Private Ryan (1998)","collaborative_similarity_score":0.9999997616,"content_similarity_score":0.9999998212,"average_similarity_score":0.9999997914,"poster_path":"\/1wY4psJ5NVEhCuOYROwLH2XExM2.jpg"},{"movieId":89.0,"title":"Schindler's List (1993)","collaborative_similarity_score":0.5882940292,"content_similarity_score":0.9487445354,"average_similarity_score":0.7685192823,"poster_path":"\/lKb6h6LURE33I3GRFYgHBUfjwSU.jpg"},{"movieId":1001.0,"title":"Good Will Hunting (1997)","collaborative_similarity_score":0.4985665977,"content_similarity_score":0.9121992588,"average_similarity_score":0.7053829283,"poster_path":"\/ylagLHIbG0F1blqSFqY6pa56Omr.jpg"},{"movieId":73.0,"title":"Apollo 13 (1995)","collaborative_similarity_score":0.5943157673,"content_similarity_score":0.7806872725,"average_similarity_score":0.6875015199,"poster_path":"\/oYUZHYMwNKnE1ef4WE5Hw2a9OAY.jpg"},{"movieId":7089.0,"title":"Wolf Hall (2015)","collaborative_similarity_score":0.4580503106,"content_similarity_score":0.9033154845,"average_similarity_score":0.6806828976,"poster_path":null},{"movieId":2492.0,"title":"Last of the Mohicans, The (1992)","collaborative_similarity_score":0.4259773195,"content_similarity_score":0.924197495,"average_similarity_score":0.6750874072,"poster_path":"\/fYVQRcgnOv998bKEplzrD3faGgt.jpg"},{"movieId":2989.0,"title":"Munich (2005)","collaborative_similarity_score":0.3794093728,"content_similarity_score":0.9619421959,"average_similarity_score":0.6706757843,"poster_path":"\/3aU825BI4IsdCPGXANqH2tqePde.jpg"},{"movieId":1717.0,"title":"Green Mile, The (1999)","collaborative_similarity_score":0.4254241884,"content_similarity_score":0.9158979058,"average_similarity_score":0.6706610471,"poster_path":"\/velWPhVMQeQKcxggNEU8YmIo52R.jpg"},{"movieId":7064.0,"title":"Woman In Berlin, A (Anonyma - Eine Frau in Berlin) (2008)","collaborative_similarity_score":0.3737285733,"content_similarity_score":0.9442340136,"average_similarity_score":0.6589812934,"poster_path":"\/pGqGnapWH4IFxUoUCZAGgjewNIj.jpg"},{"movieId":2870.0,"title":"Presumed Innocent (1990)","collaborative_similarity_score":0.3726934493,"content_similarity_score":0.9338205457,"average_similarity_score":0.6532569975,"poster_path":"\/jSPWptOsqU1nxXQe6muSPB0kD3c.jpg"}]