[{"movieId":2129.0,"title":"Hoop Dreams (1994)","collaborative_similarity_score":1.0000001192,"content_similarity_score":1.0,"average_similarity_score":1.0000000596,"poster_path":"\/7qHwh3mFJs7ldwzGSWsBLmgecfj.jpg"},{"movieId":2154.0,"title":"When We Were Kings (1996)","collaborative_similarity_score":0.6013520956,"content_similarity_score":0.7398628592,"average_similarity_score":0.6706074774,"poster_path":"\/wMnPIOYt4sNf3HMpimIzHO7L40Z.jpg"},{"movieId":17299.0,"title":"More Than a Game (2008)","collaborative_similarity_score":0.4562734365,"content_similarity_score":0.8828579783,"average_similarity_score":0.6695657074,"poster_path":"\/iiavln0DMnsd93LLfAySslKsDjj.jpg"},{"movieId":11023.0,"title":"Story of Film: An Odyssey, The (2011)","collaborative_similarity_score":0.4129473865,"content_similarity_score":0.832999289,"average_similarity_score":0.6229733378,"poster_path":"\/gkwR4Y9vv94iovYzZmHtNi8qaHl.jpg"},{"movieId":16920.0,"title":"On the Ropes (1999)","collaborative_similarity_score":0.3789980114,"content_similarity_score":0.8481971622,"average_similarity_score":0.6135975868,"poster_path":"\/naEA2Sfd3fJFIM2ooWKmVv3mvW3.jpg"},{"movieId":42683.0,"title":"Winning: The Racing Life of Paul Newman (2015)","collaborative_similarity_score":0.4200668633,"content_similarity_score":0.7834380865,"average_similarity_score":0.6017524749,"poster_path":"\/hsTxEODkmcHvVhR9junDH8I43dt.jpg"},{"movieId":9355.0,"title":"Happy Valley (2014)","collaborative_similarity_score":0.2877453566,"content_similarity_score":0.8994047046,"average_similarity_score":0.5935750306,"poster_path":"\/xyBAJKLABZrcep3IdpQovgKa6jU.jpg"},{"movieId":6579.0,"title":"Tyson (2008)","collaborative_similarity_score":0.320317924,"content_similarity_score":0.8595230579,"average_similarity_score":0.589920491,"poster_path":"\/ektR7eqmndjaYlYPciy4tJfrgh7.jpg"},{"movieId":1612.0,"title":"Spellbound (2002)","collaborative_similarity_score":0.467120558,"content_similarity_score":0.7109514475,"average_similarity_score":0.5890360028,"poster_path":"\/9tlJEmvDHjzItTT3ouR592NXooo.jpg"},{"movieId":37705.0,"title":"My Love, Don't Cross That River (2014)","collaborative_similarity_score":0.3892860413,"content_similarity_score":0.7858167291,"average_similarity_score":0.5875513852,"poster_path":"\/obrH3hsIJc472myVWi6PF86hBmL.jpg"}]