[{"movieId":565.0,"title":"No Country for Old Men (2007)","collaborative_similarity_score":0.9999998212,"content_similarity_score":1.0000001192,"average_similarity_score":0.9999999702,"poster_path":"\/6d5XOczc226jECq0LIX0siKtgHR.jpg"},{"movieId":1814.0,"title":"True Grit (2010)","collaborative_similarity_score":0.513164103,"content_similarity_score":0.847151041,"average_similarity_score":0.680157572,"poster_path":"\/krK7cQms3FlJ3HPkvXC3YyEFP2K.jpg"},{"movieId":58123.0,"title":"Lay It Down (2001)","collaborative_similarity_score":0.4836791754,"content_similarity_score":0.8188780546,"average_similarity_score":0.651278615,"poster_path":"\/vlK1Xx2YgnN3C6FJyL7ktcZxQLc.jpg"},{"movieId":12846.0,"title":"Damned United, The (2009)","collaborative_similarity_score":0.4162896872,"content_similarity_score":0.7976535559,"average_similarity_score":0.6069716215,"poster_path":"\/ftlbCma6QoRiZgiflVmLuPKHrkq.jpg"},{"movieId":607.0,"title":"Wrestler, The (2008)","collaborative_similarity_score":0.393676281,"content_similarity_score":0.8179650307,"average_similarity_score":0.6058206558,"poster_path":"\/6OTR8dSoNGjWohJNo3UhIGd3Tj.jpg"},{"movieId":14558.0,"title":"The Wild Pear Tree (2018)","collaborative_similarity_score":0.4194477201,"content_similarity_score":0.787673533,"average_similarity_score":0.6035606265,"poster_path":"\/9QNUj1e6MdyuRKxWg4v2riG97In.jpg"},{"movieId":564.0,"title":"Before the Devil Knows You're Dead (2007)","collaborative_similarity_score":0.3692806363,"content_similarity_score":0.83682096,"average_similarity_score":0.6030507982,"poster_path":"\/egIP0s1ws6fGHqTsVqVNcaEa5i2.jpg"},{"movieId":18416.0,"title":"My Happy Family (2017)","collaborative_similarity_score":0.44673419,"content_similarity_score":0.7406014204,"average_similarity_score":0.5936678052,"poster_path":"\/sCI7530hNrcCOj3SjxZAjDUxfRT.jpg"},{"movieId":30212.0,"title":"Music of Chance, The (1993)","collaborative_similarity_score":0.4164649248,"content_similarity_score":0.7705828547,"average_similarity_score":0.5935238898,"poster_path":"\/sV6CCAbmbkzlqfYMiOL9QLOMK0U.jpg"},{"movieId":24709.0,"title":"Sweet Country (2017)","collaborative_similarity_score":0.3938508928,"content_similarity_score":0.7889303565,"average_similarity_score":0.5913906246,"poster_path":"\/szJdZCSiEIYybmPymoP2UTEvOUC.jpg"}]